src/mlx_geometric/__init__.py
src/mlx_geometric/nn/conv.py
mlx_geometric-0.1.0.dist-info/METADATA
mlx_geometric-0.1.0.dist-info/WHEEL
mlx_geometric-0.1.0.dist-info/RECORD
