Metadata-Version: 2.1
Name: mlx-geometric
Version: 0.1.0
Summary: MLX library for Geometric Deep Learning.
Author: Jake Tae
Author-email: jaesungtae@gmail.com
Requires-Python: >=3.10,<4.0
Classifier: Programming Language :: Python :: 3
Classifier: Programming Language :: Python :: 3.10
Classifier: Programming Language :: Python :: 3.11
Requires-Dist: mlx (>=0.0.4,<0.0.5)
